deepl_toolkit/__init__.py
deepl_toolkit/layers.py
deepl_toolkit/utils.py
deepl_toolkit/vectors.py
deepl_toolkit-0.12.dist-info/METADATA
deepl_toolkit-0.12.dist-info/WHEEL
deepl_toolkit-0.12.dist-info/top_level.txt
deepl_toolkit-0.12.dist-info/RECORD
