Metadata-Version: 2.1
Name: deepl-toolkit
Version: 0.12
Summary: Deep Learning toolkit
Home-page: https://github.com/rs9000/deepl_toolkit
Author: Rosario (Rs)
Author-email: rs.dicarlo@gmail.com
License: MIT
Platform: UNKNOWN
Requires-Dist: torch
